localecmd/__init__.py
localecmd/builtins.py
localecmd/cli.py
localecmd/func.py
localecmd/localisation.py
localecmd/module.py
localecmd/parsing.py
localecmd/pot.py
localecmd/py.typed
localecmd/topic.py
localecmd-0.12.3.dist-info/METADATA
localecmd-0.12.3.dist-info/WHEEL
localecmd-0.12.3.dist-info/licenses/LICENCE.txt
localecmd-0.12.3.dist-info/RECORD
