Metadata-Version: 2.4
Name: localecmd
Version: 0.12.3
Summary: Python package for commandline interpreter that is translatable
Project-URL: Documentation, https://codeberg.org/jbox/localecmd
Project-URL: Issues, https://codeberg.org/jbox/localecmd/issues
Project-URL: Source, https://codeberg.org/jbox/localecmd
Author-email: j-box <j-box@blueline.email>
License-Expression: BSD-3-Clause
License-File: LICENCE.txt
Classifier: Development Status :: 4 - Beta
Classifier: Programming Language :: Python
Classifier: Programming Language :: Python :: 3
Classifier: Programming Language :: Python :: Implementation :: CPython
Classifier: Programming Language :: Python :: Implementation :: PyPy
Requires-Python: >=3.8
Requires-Dist: babel>=2.17
Requires-Dist: rich>=13
Requires-Dist: typing-extensions>=4.0
